crieur/__init__.py
crieur/__main__.py
crieur/cli.py
crieur/customistune.py
crieur/generator.py
crieur/gitutils.py
crieur/models.py
crieur/typography.py
crieur/utils.py
crieur/blog/statics/font_labeur.css
crieur/blog/statics/font_titrage.css
crieur/blog/statics/pico.css
crieur/blog/templates/article.html
crieur/blog/templates/homepage.html
crieur/blog/templates/keyword.html
crieur/blog/templates/main.html
crieur/plugins/__init__.py
crieur/plugins/bibliography.py
crieur/plugins/inline_footnotes.py
crieur/statics/font_labeur.css
crieur/statics/font_titrage.css
crieur/statics/paged-0.4.3.polyfill.min.js
crieur/statics/paged-interface-0.3.css
crieur/statics/pico.css
crieur/statics/pico_sans_plus.css
crieur/styles/apa.csl
crieur/templates/article.html
crieur/templates/article_print.html
crieur/templates/author.html
crieur/templates/authors.html
crieur/templates/base.html
crieur/templates/blog.html
crieur/templates/homepage.html
crieur/templates/keyword.html
crieur/templates/keywords.html
crieur/templates/main.html
crieur/templates/numero.html
crieur/templates/numeros.html
crieur/templates/page.html
crieur/templates/search.html
crieur-3.2.0.dist-info/METADATA
crieur-3.2.0.dist-info/WHEEL
crieur-3.2.0.dist-info/entry_points.txt
crieur-3.2.0.dist-info/licenses/LICENSE
crieur-3.2.0.dist-info/RECORD
