Metadata-Version: 2.4
Name: crieur
Version: 3.2.0
Summary: A Static Revue Generator.
Project-URL: Homepage, https://gitlab.huma-num.fr/ecrinum/crieur
Project-URL: Issues, https://gitlab.huma-num.fr/ecrinum/crieur/-/issues
Project-URL: Changelog, https://gitlab.huma-num.fr/ecrinum/crieur/-/blob/main/CHANGELOG.md?#changelog
License:                     GNU AFFERO GENERAL PUBLIC LICENSE
License-File: LICENSE
Keywords: generator,publishing,revue
Classifier: Development Status :: 5 - Production/Stable
Classifier: Intended Audience :: Education
Classifier: Intended Audience :: Information Technology
Classifier: Intended Audience :: Science/Research
Classifier: License :: OSI Approved :: GNU Affero General Public License v3
Classifier: Programming Language :: Python :: 3
Classifier: Programming Language :: Python :: 3.11
Classifier: Programming Language :: Python :: 3.12
Classifier: Programming Language :: Python :: 3.13
Classifier: Topic :: Documentation
Classifier: Topic :: Software Development :: Build Tools
Classifier: Topic :: Text Processing :: Markup :: Markdown
Requires-Python: <3.14,>=3.11
Requires-Dist: citeproc-py>=0.6.0
Requires-Dist: dataclass-wizard
Requires-Dist: feedgen>=1.0.0
Requires-Dist: httpx
Requires-Dist: jinja2
Requires-Dist: minicli
Requires-Dist: mistune>=3.1.4
Requires-Dist: pillow
Requires-Dist: python-slugify
Requires-Dist: pytz>=2025.2
Requires-Dist: pyyaml>=6.0.2
Requires-Dist: regex>=2024.11.6
Requires-Dist: tzdata>=2025.2
Requires-Dist: unidecode
Provides-Extra: dev
Requires-Dist: black; extra == 'dev'
Requires-Dist: cogapp; extra == 'dev'
Requires-Dist: hatch; extra == 'dev'
Requires-Dist: isort; extra == 'dev'
Requires-Dist: pytest; extra == 'dev'
Requires-Dist: ruff; extra == 'dev'
